{"rosters":{"franchise":[{"player":[{"status":"ROSTER","id":"7401"},{"status":"ROSTER","id":"11657"},{"status":"ROSTER","id":"9988"},{"status":"ROSTER","id":"13130"},{"id":"6789","status":"ROSTER"},{"id":"12611","status":"ROSTER"},{"status":"ROSTER","id":"12152"},{"status":"ROSTER","id":"13319"},{"status":"ROSTER","id":"10960"},{"id":"12626","status":"ROSTER"},{"id":"12620","status":"INJURED_RESERVE"},{"status":"INJURED_RESERVE","id":"11673"},{"status":"INJURED_RESERVE","id":"12647"}],"week":"16","id":"0001"},{"week":"16","player":[{"id":"12150","status":"ROSTER"},{"id":"11232","status":"ROSTER"},{"id":"13303","status":"ROSTER"},{"status":"ROSTER","id":"7813"},{"id":"13354","status":"ROSTER"},{"status":"ROSTER","id":"12186"},{"id":"10948","status":"ROSTER"},{"status":"ROSTER","id":"12140"},{"id":"9525","status":"ROSTER"},{"status":"ROSTER","id":"10276"},{"id":"11384","status":"INJURED_RESERVE"},{"status":"INJURED_RESERVE","id":"11679"}],"id":"0002"},{"week":"16","player":[{"id":"10273","status":"ROSTER"},{"status":"ROSTER","id":"10261"},{"id":"13132","status":"ROSTER"},{"id":"12610","status":"ROSTER"},{"id":"13129","status":"ROSTER"},{"id":"12610","status":"INJURED_RESERVE"},{"status":"INJURED_RESERVE","id":"13129"}],"id":"0003"},{"week":"16","player":[{"id":"12616","status":"ROSTER"},{"id":"12154","status":"ROSTER"},{"status":"ROSTER","id":"10487"},{"id":"11644","status":"ROSTER"},{"status":"ROSTER","id":"13153"},{"id":"11675","status":"ROSTER"},{"id":"12184","status":"ROSTER"},{"status":"ROSTER","id":"10903"},{"id":"7877","status":"ROSTER"},{"id":"11193","status":"ROSTER"},{"id":"10695","status":"INJURED_RESERVE"},{"status":"INJURED_RESERVE","id":"10983"},{"id":"12175","status":"INJURED_RESERVE"},{"status":"INJURED_RESERVE","id":"13131"},{"id":"8658","status":"INJURED_RESERVE"}],"id":"0004"},{"player":[{"status":"ROSTER","id":"7394"},{"status":"ROSTER","id":"10703"},{"status":"ROSTER","id":"10302"},{"status":"ROSTER","id":"9118"},{"id":"10708","status":"ROSTER"},{"id":"8359","status":"ROSTER"},{"status":"ROSTER","id":"9319"},{"status":"ROSTER","id":"13290"},{"status":"ROSTER","id":"12181"},{"status":"ROSTER","id":"10738"}],"week":"16","id":"0005"},{"player":[{"status":"ROSTER","id":"5848"},{"id":"12151","status":"ROSTER"},{"id":"9448","status":"ROSTER"},{"status":"ROSTER","id":"9902"},{"status":"ROSTER","id":"10527"},{"status":"ROSTER","id":"8742"},{"id":"8930","status":"ROSTER"},{"id":"7393","status":"ROSTER"},{"status":"ROSTER","id":"9064"},{"status":"ROSTER","id":"10313"}],"week":"16","id":"0006"},{"week":"16","player":[{"id":"11192","status":"ROSTER"},{"id":"10271","status":"ROSTER"},{"id":"4925","status":"ROSTER"},{"status":"ROSTER","id":"11642"},{"id":"9831","status":"ROSTER"},{"status":"ROSTER","id":"12628"},{"id":"13113","status":"INJURED_RESERVE"},{"status":"INJURED_RESERVE","id":"9250"},{"id":"12625","status":"INJURED_RESERVE"},{"status":"INJURED_RESERVE","id":"11186"}],"id":"0007"},{"player":[{"status":"ROSTER","id":"9431"},{"id":"9823","status":"ROSTER"},{"id":"8670","status":"ROSTER"},{"status":"ROSTER","id":"6929"},{"id":"12801","status":"ROSTER"},{"id":"11222","status":"ROSTER"},{"id":"11339","status":"ROSTER"},{"id":"11247","status":"ROSTER"},{"status":"ROSTER","id":"12157"},{"status":"INJURED_RESERVE","id":"12171"},{"id":"5666","status":"INJURED_RESERVE"},{"id":"8687","status":"INJURED_RESERVE"}],"id":"0008","week":"16"},{"player":[{"id":"12652","status":"ROSTER"},{"status":"ROSTER","id":"2842"},{"id":"11660","status":"ROSTER"},{"id":"10868","status":"ROSTER"},{"status":"ROSTER","id":"12141"},{"id":"11244","status":"ROSTER"},{"id":"9884","status":"ROSTER"},{"id":"11668","status":"ROSTER"},{"status":"ROSTER","id":"11761"},{"id":"7836","status":"ROSTER"},{"status":"INJURED_RESERVE","id":"13128"},{"id":"10722","status":"INJURED_RESERVE"}],"id":"0009","week":"16"},{"player":[{"status":"ROSTER","id":"9099"},{"status":"ROSTER","id":"12634"},{"status":"ROSTER","id":"11671"},{"status":"ROSTER","id":"13138"},{"id":"10700","status":"ROSTER"},{"id":"10976","status":"ROSTER"},{"status":"ROSTER","id":"9427"},{"status":"ROSTER","id":"10369"},{"status":"ROSTER","id":"11938"},{"status":"ROSTER","id":"11936"},{"status":"INJURED_RESERVE","id":"11678"}],"week":"16","id":"0010"}]},"encoding":"utf-8","version":"1.0"}